[
 {
  "directory": "/home/doge/CPP04/ex01",
  "arguments": [
   "g++",
   "-Wall",
   "-Wextra",
   "-Werror",
   "-std=c++98",
   "-Iincludes",
   "-g",
   "-gdwarf-4",
   "-c",
   "srcs/main.cpp",
   "-o",
   "objs/main.o"
  ],
  "file": "srcs/main.cpp"
 },
 {
  "directory": "/home/doge/CPP04/ex01",
  "arguments": [
   "g++",
   "-Wall",
   "-Wextra",
   "-Werror",
   "-std=c++98",
   "-Iincludes",
   "-g",
   "-gdwarf-4",
   "-c",
   "srcs/Cat.cpp",
   "-o",
   "objs/Cat.o"
  ],
  "file": "srcs/Cat.cpp"
 },
 {
  "directory": "/home/doge/CPP04/ex01",
  "arguments": [
   "g++",
   "-Wall",
   "-Wextra",
   "-Werror",
   "-std=c++98",
   "-Iincludes",
   "-g",
   "-gdwarf-4",
   "-c",
   "srcs/Dog.cpp",
   "-o",
   "objs/Dog.o"
  ],
  "file": "srcs/Dog.cpp"
 },
 {
  "directory": "/home/doge/CPP04/ex01",
  "arguments": [
   "g++",
   "-Wall",
   "-Wextra",
   "-Werror",
   "-std=c++98",
   "-Iincludes",
   "-g",
   "-gdwarf-4",
   "-c",
   "srcs/Animal.cpp",
   "-o",
   "objs/Animal.o"
  ],
  "file": "srcs/Animal.cpp"
 },
 {
  "directory": "/home/doge/CPP04/ex01",
  "arguments": [
   "g++",
   "-Wall",
   "-Wextra",
   "-Werror",
   "-std=c++98",
   "-Iincludes",
   "-g",
   "-gdwarf-4",
   "-c",
   "srcs/WrongAnimal.cpp",
   "-o",
   "objs/WrongAnimal.o"
  ],
  "file": "srcs/WrongAnimal.cpp"
 },
 {
  "directory": "/home/doge/CPP04/ex01",
  "arguments": [
   "g++",
   "-Wall",
   "-Wextra",
   "-Werror",
   "-std=c++98",
   "-Iincludes",
   "-g",
   "-gdwarf-4",
   "-c",
   "srcs/WrongCat.cpp",
   "-o",
   "objs/WrongCat.o"
  ],
  "file": "srcs/WrongCat.cpp"
 },
 {
  "directory": "/home/doge/CPP04/ex01",
  "arguments": [
   "g++",
   "-Wall",
   "-Wextra",
   "-Werror",
   "-std=c++98",
   "-Iincludes",
   "-g",
   "-gdwarf-4",
   "-c",
   "srcs/Brain.cpp",
   "-o",
   "objs/Brain.o"
  ],
  "file": "srcs/Brain.cpp"
 }
]
